rocc
