Metadata-Version: 2.1
Name: rocc
Version: 2.0.0
Summary: Rate-of-change check of time series
Home-page: https://github.com/openmeteo/rocc
Author: Antonis Christofides
Author-email: antonis@antonischristofides.com
License: GNU General Public License v3
Platform: UNKNOWN
Classifier: Development Status :: 2 - Pre-Alpha
Classifier: Intended Audience :: Developers
Classifier: License :: OSI Approved :: GNU General Public License v3 (GPLv3)
Classifier: Natural Language :: English
Classifier: Programming Language :: Python :: 3.7
